openbiolink/__init__.py
openbiolink/__main__.py
openbiolink/cli.py
openbiolink/cli_helper.py
openbiolink/edge.py
openbiolink/edgeType.py
openbiolink/globalConfig.py
openbiolink/graphProperties.py
openbiolink/namespace.py
openbiolink/node.py
openbiolink/nodeType.py
openbiolink/openBioLink.py
openbiolink/utils.py
openbiolink/evaluation/__init__.py
openbiolink/evaluation/dataLoader.py
openbiolink/evaluation/evaluation.py
openbiolink/graph_creation/__init__.py
openbiolink/graph_creation/graphCreation.py
openbiolink/graph_creation/graphCreationConfig.py
openbiolink/graph_creation/graphCreator.py
openbiolink/graph_creation/file_downloader/__init__.py
openbiolink/graph_creation/file_downloader/fileDownloader.py
openbiolink/graph_creation/file_processor/__init__.py
openbiolink/graph_creation/file_processor/fileProcessor.py
openbiolink/graph_creation/file_processor/myFileProcessor.py
openbiolink/graph_creation/file_processor/edge/__init__.py
openbiolink/graph_creation/file_processor/edge/edgeBgeeExprProcessor.py
openbiolink/graph_creation/file_processor/edge/edgeBgeeNoExprProcessor.py
openbiolink/graph_creation/file_processor/edge/edgeBgeeOverExprProcessor.py
openbiolink/graph_creation/file_processor/edge/edgeBgeeUnderExprProcessor.py
openbiolink/graph_creation/file_processor/edge/edgeCdtPathProcessor.py
openbiolink/graph_creation/file_processor/edge/edgeDisGeNetProcessor.py
openbiolink/graph_creation/file_processor/edge/edgeDrugCentralContraIndProcessor.py
openbiolink/graph_creation/file_processor/edge/edgeDrugCentralIndProcessor.py
openbiolink/graph_creation/file_processor/edge/edgeGoProcessor.py
openbiolink/graph_creation/file_processor/edge/edgeHpaProcessor.py
openbiolink/graph_creation/file_processor/edge/edgeHpoDisProcessor.py
openbiolink/graph_creation/file_processor/edge/edgeHpoGeneProcessor.py
openbiolink/graph_creation/file_processor/edge/edgeSiderIndProcessor.py
openbiolink/graph_creation/file_processor/edge/edgeSiderSeProcessor.py
openbiolink-0.1.4.dist-info/LICENSE
openbiolink-0.1.4.dist-info/METADATA
openbiolink-0.1.4.dist-info/WHEEL
openbiolink-0.1.4.dist-info/entry_points.txt
openbiolink-0.1.4.dist-info/top_level.txt
openbiolink-0.1.4.dist-info/RECORD
