Metadata-Version: 2.1
Name: openbiolink
Version: 0.1.4
Summary: A framework for the OpenBioLink knowledge graph
Home-page: https://github.com/OpenBioLink/OpenBioLink
Author: Anna Breit, Matthias Samwald, Simon Ott, Laura Graf, Asan Agibetov
Author-email: matthiassamwald@gmail.com
License: UNKNOWN
Platform: UNKNOWN
Classifier: Programming Language :: Python :: 3
Classifier: License :: OSI Approved :: MIT License
Classifier: Operating System :: OS Independent
Requires-Python: >=3.6
License-File: LICENSE
Requires-Dist: click
Requires-Dist: numpy
Requires-Dist: pandas (>=0.23.4)
Requires-Dist: tqdm (>=4.29.1)
Requires-Dist: torch
Provides-Extra: docs
Requires-Dist: sphinx ; extra == 'docs'
Requires-Dist: sphinx-rtd-theme ; extra == 'docs'
Requires-Dist: sphinx-click ; extra == 'docs'
Requires-Dist: sphinx-autodoc-typehints ; extra == 'docs'
Requires-Dist: sphinx-automodapi ; extra == 'docs'
Requires-Dist: texext ; extra == 'docs'
